kdl_wagtail_page/__init__.py
kdl_wagtail_page/admin.py
kdl_wagtail_page/apps.py
kdl_wagtail_page/models.py
kdl_wagtail_page/tests.py
kdl_wagtail_page/views.py
kdl_wagtail_page/migrations/0001_initial.py
kdl_wagtail_page/migrations/__init__.py
kdl_wagtail_page/templates/kdl_wagtail_page/rich_page.html
kdl_wagtail_page-0.1.2.dist-info/DESCRIPTION.rst
kdl_wagtail_page-0.1.2.dist-info/METADATA
kdl_wagtail_page-0.1.2.dist-info/RECORD
kdl_wagtail_page-0.1.2.dist-info/WHEEL
kdl_wagtail_page-0.1.2.dist-info/metadata.json
kdl_wagtail_page-0.1.2.dist-info/top_level.txt
