Metadata-Version: 2.0
Name: kdl-wagtail-page
Version: 0.1.2
Summary: Basic but reusable Wagtail page models for KDL projects
Home-page: https://github.com/kingsdigitallab/kdl-wagtail-page
Author: Geoffroy Noel
Author-email: geoffroy.noel@kcl.ac.uk
License: MIT
Platform: UNKNOWN
Requires-Python: >3.5
Requires-Dist: wagtail (>=2.0)
